{
  "HERO": "Pip",
  "HERO_ROLE": "the smallest lightning bug",
  "COMPANION": "wise old Frog",
  "THRESHOLD": "the warm garden pond at night",
  "HOME": "his cozy leaf hammock",
  "ENTRANCE": "his own lily pad perch",
  "OPENING_MOMENT": "twilight, as the garden turns gold",
  "HERO_FEATURE": "wings",
  "CLIMB_AID": "a floating lily pad",
  "CHILDREN": "rabbits in the burrow",
  "ROUTE_A_CHAR": "the shady fern",
  "ROUTE_B_CHAR": "a quick wing flutter",
  "ROUTE_C_CHAR": "the pond below",
  "A2_FIND": "a snail",
  "B1_LANDING": "a patch of moss",
  "B2_SCENE": "the reeds far below",
  "WIGGLE_GLITTER": "tiny gold sparks",
  "SLIDE_LOW": "the lily pads",
  "LOW_HOUSES": "small burrows with soft glowing lanterns",
  "LULLABY_SONG": "a humming tune",
  "OTHER_STARS": "the other garden lightning bugs",
  "GOODNIGHT_PRIZE": "Sleepy Garden",
  "LULLABY_PRIZE": "Hum",
  "FRIENDS_PRIZE": "A Garden Full of Lights"
}
