{
  "HERO": "Priya",
  "THRESHOLD": "the Coral Bay Aquarium",
  "HUB": "the atrium",
  "FOUNDER": "the founder",
  "GUARD": "the night watchman",
  "CURATOR": "the head biologist",
  "MARK": "silver anchor mark",
  "KEY_ITEM": "the tarnished silver key",
  "CODE": "the folded cipher slip",
  "CIPHER_TOOL": "the decoder ring",
  "MAP": "the creased blueprint",
  "GOAL": "sunken exhibit",
  "STUDY_TABLE": "chart table",
  "ROUTE_A_PLACE": "the Shark Tunnel",
  "ROUTE_B_PLACE": "the Reef Wing",
  "ROUTE_C_PLACE": "the old Ledger Room",
  "A1_SIGN": "a huge shark tank",
  "A1_LANDMARK1": "a smudged viewing pane",
  "A1_LANDMARK2": "a tiny tag fallen behind it",
  "A2_SIGN": "a faint sonar ping",
  "A2_GATE": "Caught at the Tank",
  "ROUTE_A_PASSAGE": "a maintenance tunnel",
  "ROUTE_A_LOCK": "a small sealed hatch",
  "ROUTE_A_CACHE": "a loose floor grate",
  "B1_SIGN": "a huge coral pillar",
  "B1_LID": "the cracked lid",
  "B1_LANDMARK": "a shell display",
  "B2_SIGN": "a faded exhibit chart",
  "B2_TORCH": "a spare flashlight",
  "B2_GATE": "The Curtained Tank Room",
  "ROUTE_B_PASSAGE": "a narrow walkway",
  "ROUTE_B_LOCK": "another small sealed hatch",
  "ROUTE_B_CACHE": "one loose ceiling panel",
  "C1_SIGN": "a dusty guest register",
  "C1_INDEX": "a card catalogue",
  "C1_DRAWER": "a jammed side drawer",
  "C1_CARD": "an out-of-place catalogue card",
  "C1_PLAN": "a folded chart with one tank circled",
  "ROUTE_C_VAULT": "a low locker",
  "ROUTE_C_CACHE": "a narrow gap behind the binders",
  "C2_SIGN": "the back archives",
  "C2_GATE": "Lost in the Archives",
  "C2_LANTERN": "a wind-up lantern",
  "KEY_A_PLACE": "office",
  "KEY_B_PLACE": "sealed specimen case",
  "KEY_C_PLACE": "maintenance stairs",
  "KA_DESK": "a battered rolltop desk",
  "KA_PORTRAIT": "a faded photograph",
  "KA_NOTEBOOK": "a salt-stained notebook",
  "KB_JOURNALS": "expedition logs",
  "KB_LEDGER": "a thin logbook",
  "KB_GATE": "The Cracked Pane",
  "KC_CUPBOARD": "a narrow locker",
  "KC_CHART": "a rolled chart",
  "CIPHER_CLUE": "follow the tide",
  "CIPHER_A_PLACE": "the Tide Hall",
  "CIPHER_B_PLACE": "the Chart Room",
  "CIPHER_C_PLACE": "the Pump Corridor",
  "CA_DOME": "a painted wave mural",
  "CA_LADDER": "a service ladder",
  "CA_CATWALK": "a narrow gangway",
  "CA_GATE": "High on the Gangway",
  "CB_GLOBE": "a great tide model",
  "CB_ATLAS": "a giant bound chart book",
  "CC_GEARS": "the pump room",
  "CC_PENDULUM": "a slow, heavy valve wheel",
  "CC_GATE": "Under the Valve",
  "RA_GLOBE": "a great tide model of brass gears",
  "RB_PEDESTAL": "the console",
  "RC_ROOM": "watch room",
  "RA_STAIR": "a hatch going down",
  "RA_GATE": "The Jammed Gears",
  "RB_WORKSHOP": "a dusty room crowded with half-built dioramas",
  "RB_PRIZE": "The Hidden Workshop",
  "RC_LOG": "a watch log",
  "RC_PHONE": "a heavy black telephone",
  "RC_RESULT": "The Call for a Ride",
  "V_CHAMBER": "vault",
  "V_LETTER": "a sealed letter",
  "V_MAP": "an old salvage chart",
  "VA_CATALOGUE": "inventory",
  "VA_PRIZE1": "The Full Story",
  "VA_PRIZE2": "Keeper of the Note",
  "VB_WING": "a flooded wing",
  "VB_GALLERY": "a small sealed tank room",
  "VB_PRIZE1": "The Flooded Wing",
  "VB_RESULT1": "Proof in a Photo",
  "VB_GATE": "Out of Night",
  "VC_PRIZE1": "Morning Heroes",
  "VC_PRIZE2": "A Secret Among Friends",
  "VC_PRIZE3": "Left for the Light",
  "VD_OWL": "a small crystal seahorse",
  "VD_GATE": "Caught Red-Handed",
  "VD_RESULT": "Wiser by Morning"
}
